AUTHORS.rst
LICENSE
MANIFEST.in
Makefile
README.rst
setup.py
pyprof2html/__init__.py
pyprof2html/_compat.py
pyprof2html/_version.py
pyprof2html/commands.py
pyprof2html/core.py
pyprof2html/environment.py
pyprof2html.egg-info/PKG-INFO
pyprof2html.egg-info/SOURCES.txt
pyprof2html.egg-info/dependency_links.txt
pyprof2html.egg-info/entry_points.txt
pyprof2html.egg-info/not-zip-safe
pyprof2html.egg-info/requires.txt
pyprof2html.egg-info/top_level.txt
pyprof2html/templates/arrow.png.base64
pyprof2html/templates/base.html
pyprof2html/templates/callers.html
pyprof2html/templates/hotshot-line.html
pyprof2html/templates/jquery.js
pyprof2html/templates/jquery.tablesorter.min.js
pyprof2html/templates/main.html
pyprof2html/templates/style.css
test/test_pyprof2html.py