Metadata-Version: 1.1
Name: pyprof2html
Version: 0.3.2
Summary: Python cProfile and hotshot profile's data to HTML Converter
Home-page: https://bitbucket.org/hhatto/pyprof2html
Author: Hideo Hattori
Author-email: hhatto.jp@gmail.com
License: New BSD License
Keywords: profile visualize html
Platform: UNKNOWN
Classifier: Development Status :: 4 - Beta
Classifier: Intended Audience :: Developers
Classifier: Environment :: Console
Classifier: Operating System :: Unix
Classifier: License :: OSI Approved :: BSD License
Classifier: Programming Language :: Python
Classifier: Programming Language :: Python :: 2
Classifier: Programming Language :: Python :: 2.7
Classifier: Programming Language :: Python :: 3.4
Classifier: Topic :: Software Development
